lacquer/__init__.py
lacquer/reserved.py
lacquer/utils.py
lacquer/formatter/__init__.py
lacquer/formatter/formatter.py
lacquer/parsers/__init__.py
lacquer/parsers/expression_parser_table.py
lacquer/parsers/lexer.py
lacquer/parsers/parser.py
lacquer/parsers/parser_table.py
lacquer/tree/__init__.py
lacquer/tree/approximate.py
lacquer/tree/call_argument.py
lacquer/tree/explain.py
lacquer/tree/expression.py
lacquer/tree/grouping.py
lacquer/tree/join_criteria.py
lacquer/tree/literal.py
lacquer/tree/node.py
lacquer/tree/qualified_name.py
lacquer/tree/query_specification.py
lacquer/tree/relation.py
lacquer/tree/rewrite.py
lacquer/tree/select.py
lacquer/tree/select_item.py
lacquer/tree/set_operation.py
lacquer/tree/sort_item.py
lacquer/tree/statement.py
lacquer/tree/table.py
lacquer/tree/table_element.py
lacquer/tree/transaction.py
lacquer/tree/values.py
lacquer/tree/visitor.py
lacquer/tree/window.py
lacquer-0.1.dist-info/DESCRIPTION.rst
lacquer-0.1.dist-info/METADATA
lacquer-0.1.dist-info/RECORD
lacquer-0.1.dist-info/WHEEL
lacquer-0.1.dist-info/metadata.json
lacquer-0.1.dist-info/top_level.txt
