Metadata-Version: 2.0
Name: lacquer
Version: 0.1
Summary: A SQL Parser based on the parser in the presto project
Home-page: http://github.com/slaclab/lacquer
Author: Brian Van Klaveren
Author-email: bvan@slac.stanford.edu
License: Apache License 2.0
Platform: UNKNOWN
Classifier: Intended Audience :: Developers
Classifier: Intended Audience :: Science/Research
Classifier: License :: OSI Approved :: Apache Software License
Classifier: Operating System :: OS Independent
Classifier: Programming Language :: Python
Classifier: Programming Language :: Python :: 2
Classifier: Programming Language :: Python :: 2.7
Classifier: Programming Language :: Python :: 3
Classifier: Programming Language :: Python :: 3.5
Classifier: Topic :: Database :: Database Engines/Servers
Classifier: Topic :: Database :: Front-Ends
Classifier: Topic :: Software Development :: Compilers
Requires-Dist: future
Requires-Dist: ply
